animal_data_analysis_tools/__init__.py
animal_data_analysis_tools/__main__.py
wa_weather_station_tool/__init__.py
wa_weather_station_tool/__main__.py
wa_weather_station_tool/cli.py
wa_weather_station_tool/downloader.py
wa_weather_station_tool-0.1.0.dist-info/METADATA
wa_weather_station_tool-0.1.0.dist-info/WHEEL
wa_weather_station_tool-0.1.0.dist-info/entry_points.txt
wa_weather_station_tool-0.1.0.dist-info/RECORD
