Metadata-Version: 2.4
Name: wa-weather-station-tool
Version: 0.1.0
Summary: WA DPIRD weather station downloader (minimal CLI)
Author: Animal Data Analysis Tools
License: Proprietary
Keywords: CLI,DPIRD,WA,downloader,weather
Classifier: License :: Other/Proprietary License
Classifier: Operating System :: OS Independent
Classifier: Programming Language :: Python :: 3
Classifier: Programming Language :: Python :: 3 :: Only
Requires-Python: >=3.10
